g4f/__init__.py
g4f/cli.py
g4f/debug.py
g4f/errors.py
g4f/models.py
g4f/requests.py
g4f/typing.py
g4f/webdriver.py
g4f/Provider/AItianhu.py
g4f/Provider/AItianhuSpace.py
g4f/Provider/AiAsk.py
g4f/Provider/AiChatOnline.py
g4f/Provider/Aichat.py
g4f/Provider/Berlin.py
g4f/Provider/Bing.py
g4f/Provider/ChatAnywhere.py
g4f/Provider/ChatBase.py
g4f/Provider/ChatForAi.py
g4f/Provider/Chatgpt4Online.py
g4f/Provider/ChatgptAi.py
g4f/Provider/ChatgptDemo.py
g4f/Provider/ChatgptDemoAi.py
g4f/Provider/ChatgptFree.py
g4f/Provider/ChatgptLogin.py
g4f/Provider/ChatgptNext.py
g4f/Provider/ChatgptX.py
g4f/Provider/DeepInfra.py
g4f/Provider/FakeGpt.py
g4f/Provider/FreeGpt.py
g4f/Provider/GPTalk.py
g4f/Provider/GeekGpt.py
g4f/Provider/GptChatly.py
g4f/Provider/GptForLove.py
g4f/Provider/GptGo.py
g4f/Provider/GptGod.py
g4f/Provider/GptTalkRu.py
g4f/Provider/Hashnode.py
g4f/Provider/Koala.py
g4f/Provider/Liaobots.py
g4f/Provider/Llama2.py
g4f/Provider/MyShell.py
g4f/Provider/OnlineGpt.py
g4f/Provider/Opchatgpts.py
g4f/Provider/PerplexityAi.py
g4f/Provider/Phind.py
g4f/Provider/Pi.py
g4f/Provider/TalkAi.py
g4f/Provider/Vercel.py
g4f/Provider/Ylokh.py
g4f/Provider/You.py
g4f/Provider/Yqcloud.py
g4f/Provider/__init__.py
g4f/Provider/base_provider.py
g4f/Provider/helper.py
g4f/Provider/retry_provider.py
g4f/Provider/deprecated/Acytoo.py
g4f/Provider/deprecated/AiService.py
g4f/Provider/deprecated/Aibn.py
g4f/Provider/deprecated/Ails.py
g4f/Provider/deprecated/Aivvm.py
g4f/Provider/deprecated/ChatgptDuo.py
g4f/Provider/deprecated/CodeLinkAva.py
g4f/Provider/deprecated/Cromicle.py
g4f/Provider/deprecated/DfeHub.py
g4f/Provider/deprecated/EasyChat.py
g4f/Provider/deprecated/Equing.py
g4f/Provider/deprecated/FastGpt.py
g4f/Provider/deprecated/Forefront.py
g4f/Provider/deprecated/GetGpt.py
g4f/Provider/deprecated/H2o.py
g4f/Provider/deprecated/Lockchat.py
g4f/Provider/deprecated/Myshell.py
g4f/Provider/deprecated/NoowAi.py
g4f/Provider/deprecated/V50.py
g4f/Provider/deprecated/Vitalentum.py
g4f_fork-0.1.9.5.dist-info/LICENSE
g4f_fork-0.1.9.5.dist-info/METADATA
g4f_fork-0.1.9.5.dist-info/WHEEL
g4f_fork-0.1.9.5.dist-info/entry_points.txt
g4f_fork-0.1.9.5.dist-info/top_level.txt
g4f_fork-0.1.9.5.dist-info/RECORD
